Metadata-Version: 2.1
Name: doc2mds
Version: 1.0
Summary: doc2mds: Convert docstring to markdown files
Author-email: Yijie Xia <yijiexia@pku.edu.cn>
License: ##############################################################################
Keywords: docstring,markdown
Classifier: Development Status :: 5 - Production/Stable
Classifier: License :: OSI Approved :: Apache Software License
Classifier: Programming Language :: Python :: 3
Classifier: Operating System :: POSIX :: Linux
Classifier: Operating System :: Microsoft :: Windows
License-File: LICENSE
